tkdraw/__init__.py
tkdraw/basic.py
tkdraw/screen.py
tkdraw/test/__init__.py
tkdraw/test/__main__.py
tkdraw/test/test_basic.py
tkdraw/test/test_screen.py
tkdraw-1.0.1.dist-info/LICENSE
tkdraw-1.0.1.dist-info/METADATA
tkdraw-1.0.1.dist-info/WHEEL
tkdraw-1.0.1.dist-info/top_level.txt
tkdraw-1.0.1.dist-info/RECORD
