Metadata-Version: 2.1
Name: tkdraw
Version: 1.0.1
Summary: A basic synchronous draw GUI based on tkinter
Home-page: https://github.com/vincentloechner/pytkdraw.git
Author: Vincent Loechner
Author-email: loechner@unistra.fr
Project-URL: Bug Tracker, https://github.com/vincentloechner/pytkdraw/issues
Project-URL: Documentation, https://vincentloechner.github.io/pytkdraw/tkdraw/
Classifier: Development Status :: 4 - Beta
Classifier: Programming Language :: Python :: 3
Classifier: License :: OSI Approved :: MIT License
Classifier: Operating System :: OS Independent
Classifier: Topic :: Software Development :: Libraries :: Python Modules
Classifier: Topic :: Software Development :: User Interfaces
Requires-Python: >=3.6
License-File: LICENSE
